LICENSE
README.md
setup.py
weather_generator/Hyperexponential_dist.py
weather_generator/__init__.py
weather_generator/rain_weather_generator.py
weather_generator.egg-info/PKG-INFO
weather_generator.egg-info/SOURCES.txt
weather_generator.egg-info/dependency_links.txt
weather_generator.egg-info/not-zip-safe
weather_generator.egg-info/top_level.txt