Metadata-Version: 2.1
Name: weather-generator
Version: 0.1
Summary: Stochastic weather daily generator
Author: Farafehizoro Ramanjatonirina
License: UNKNOWN
Platform: UNKNOWN
License-File: LICENSE
